MountainRed/__init__.py
MountainRed/__main__.py
MountainRed/settings.py
MountainRed/urls.py
MountainRed/wsgi.py
MountainRed/core/__init__.py
MountainRed/core/db_loader.py
MountainRed/core/meta_reflex.py
MountainRed/core/router.py
MountainRed/dbsm/__init__.py
MountainRed/dbsm/__main__.py
MountainRed/dbsm/models.py
MountainRed/dbsm/loaders/__init__.py
MountainRed/dbsm/loaders/mysql.py
MountainRed/dbsm/loaders/oracle.py
MountainRed/dbsm/loaders/postgre.py
MountainRed/dbsm/loaders/sqlite.py
MountainRed/dbsm/writers/__init__.py
MountainRed/dbsm/writers/mysql.py
MountainRed/dbsm/writers/oracle.py
MountainRed/dbsm/writers/postgre.py
MountainRed/dbsm/writers/sqlite.py
MountainRed/mixin/__init__.py
MountainRed/mixin/hook.py
MountainRed/utils/__init__.py
MountainRed/utils/cli.py
MountainRed/utils/common.py
MountainRed/utils/logging.py
MountainRed/utils/logo.py
MountainRed/views/__init__.py
MountainRed/views/api.py
MountainRed/views/render.py
MountainRed/views/templates/index.html
MountainRed-0.2.0.dist-info/AUTHORS
MountainRed-0.2.0.dist-info/LICENSE
MountainRed-0.2.0.dist-info/METADATA
MountainRed-0.2.0.dist-info/WHEEL
MountainRed-0.2.0.dist-info/pbr.json
MountainRed-0.2.0.dist-info/top_level.txt
MountainRed-0.2.0.dist-info/RECORD
