Metadata-Version: 2.1
Name: MountainRed
Version: 0.2.0
Summary: Django-ORM based DataBase tool
Home-page: http://example.com
Author: singein
Author-email: singein@outlook.com
License: MIT
Platform: UNKNOWN
